ACPy/__init__.py
ACPy/ac_acim.py
ACPy/ac_cut.py
ACPy/ac_gh_data_wrapper.py
ACPy/ac_hole.py
ACPy/ac_jointdetector.py
ACPy/ac_transformations.py
ACPy/ac_util.py
ACPy/main.py
augmented_carpentry_py-1.0.0.dist-info/METADATA
augmented_carpentry_py-1.0.0.dist-info/WHEEL
augmented_carpentry_py-1.0.0.dist-info/top_level.txt
augmented_carpentry_py-1.0.0.dist-info/RECORD
