Metadata-Version: 2.2
Name: augmented-carpentry-py
Version: 1.0.0
Summary: AugmentedCarpentryPy for the Augmented Carpentry research at IBOIS, EPFL.
Home-page: https://github.com/ibois-epfl/augmented-carpentry
Author: Andrea Settimi
Author-email: andrea.settimi@epfl.ch
Classifier: License :: OSI Approved :: MIT License
Classifier: Programming Language :: Python :: 3
Classifier: Programming Language :: Python :: 3.9
Requires-Dist: numpy
Dynamic: author
Dynamic: author-email
Dynamic: classifier
Dynamic: description
Dynamic: description-content-type
Dynamic: home-page
Dynamic: requires-dist
Dynamic: summary
